lia/__init__.py
lia/exceptions.py
lia/protocols.py
lia/py.typed
lia/response.py
lia/request/__init__.py
lia/request/_aiohttp.py
lia/request/_base.py
lia/request/_chalice.py
lia/request/_django.py
lia/request/_flask.py
lia/request/_litestar.py
lia/request/_quart.py
lia/request/_sanic.py
lia/request/_starlette.py
lia/request/_testing.py
lia_web-0.3.0.dist-info/METADATA
lia_web-0.3.0.dist-info/WHEEL
lia_web-0.3.0.dist-info/RECORD
