Metadata-Version: 2.4
Name: lia-web
Version: 0.3.0
Summary: This package has been renamed to cross-web. Install cross-web instead.
Author-email: Patrick Arminio <patrick.arminio@gmail.com>
Classifier: Development Status :: 7 - Inactive
Classifier: Intended Audience :: Developers
Classifier: License :: OSI Approved :: MIT License
Classifier: Topic :: Software Development :: Libraries
Classifier: Topic :: Software Development :: Libraries :: Python Modules
Requires-Python: >=3.9
Requires-Dist: cross-web>=0.2.3
